strands_evals/__init__.py
strands_evals/case.py
strands_evals/experiment.py
strands_evals/display/display_console.py
strands_evals/evaluators/__init__.py
strands_evals/evaluators/evaluator.py
strands_evals/evaluators/faithfulness_evaluator.py
strands_evals/evaluators/goal_success_rate_evaluator.py
strands_evals/evaluators/harmfulness_evaluator.py
strands_evals/evaluators/helpfulness_evaluator.py
strands_evals/evaluators/interactions_evaluator.py
strands_evals/evaluators/output_evaluator.py
strands_evals/evaluators/tool_parameter_accuracy_evaluator.py
strands_evals/evaluators/tool_selection_accuracy_evaluator.py
strands_evals/evaluators/trajectory_evaluator.py
strands_evals/evaluators/prompt_templates/case_prompt_template.py
strands_evals/evaluators/prompt_templates/prompt_templates.py
strands_evals/evaluators/prompt_templates/faithfulness/__init__.py
strands_evals/evaluators/prompt_templates/faithfulness/faithfulness_v0.py
strands_evals/evaluators/prompt_templates/goal_success_rate/__init__.py
strands_evals/evaluators/prompt_templates/goal_success_rate/goal_success_rate_v0.py
strands_evals/evaluators/prompt_templates/harmfulness/__init__.py
strands_evals/evaluators/prompt_templates/harmfulness/harmfulness_v0.py
strands_evals/evaluators/prompt_templates/helpfulness/__init__.py
strands_evals/evaluators/prompt_templates/helpfulness/helpfulness_v0.py
strands_evals/evaluators/prompt_templates/tool_parameter_accuracy/__init__.py
strands_evals/evaluators/prompt_templates/tool_parameter_accuracy/tool_parameter_accuracy_v0.py
strands_evals/evaluators/prompt_templates/tool_selection_accuracy/__init__.py
strands_evals/evaluators/prompt_templates/tool_selection_accuracy/tool_selection_accuracy_v0.py
strands_evals/extractors/__init__.py
strands_evals/extractors/graph_extractor.py
strands_evals/extractors/swarm_extractor.py
strands_evals/extractors/tools_use_extractor.py
strands_evals/extractors/trace_extractor.py
strands_evals/generators/__init__.py
strands_agents_evals-0.1.3.dist-info/METADATA
strands_agents_evals-0.1.3.dist-info/WHEEL
strands_agents_evals-0.1.3.dist-info/licenses/LICENSE
strands_agents_evals-0.1.3.dist-info/licenses/NOTICE
strands_agents_evals-0.1.3.dist-info/RECORD
