Metadata-Version: 2.4
Name: strands-agents-evals
Version: 0.1.3
Summary: Evaluation framework for Strands
Author-email: AWS <opensource@amazon.com>
License: Apache-2.0
License-File: LICENSE
License-File: NOTICE
Requires-Python: >=3.10
Requires-Dist: boto3>=1.26.0
Requires-Dist: opentelemetry-api>=1.20.0
Requires-Dist: opentelemetry-instrumentation-threading<1.00b0,>=0.51b0
Requires-Dist: opentelemetry-sdk>=1.20.0
Requires-Dist: pydantic<3.0.0,>=2.0.0
Requires-Dist: rich<15.0.0,>=14.0.0
Requires-Dist: strands-agents-tools<1.0.0,>=0.1.0
Requires-Dist: strands-agents>=1.0.0
Requires-Dist: typing-extensions>=4.0
Provides-Extra: dev
Requires-Dist: hatch<2.0.0,>=1.0.0; extra == 'dev'
Requires-Dist: mypy<2.0.0,>=1.15.0; extra == 'dev'
Requires-Dist: pre-commit<4.6.0,>=3.2.0; extra == 'dev'
Requires-Dist: ruff<0.15.0,>=0.13.0; extra == 'dev'
Provides-Extra: otel
Requires-Dist: opentelemetry-exporter-otlp-proto-http<2.0.0,>=1.30.0; extra == 'otel'
Provides-Extra: test
Requires-Dist: pytest-asyncio<1.4.0,>=1.0.0; extra == 'test'
Requires-Dist: pytest-cov<8.0.0,>=7.0.0; extra == 'test'
Requires-Dist: pytest-xdist<4.0.0,>=3.0.0; extra == 'test'
Requires-Dist: pytest<10.0.0,>=8.0.0; extra == 'test'
